builder/__init__.py
builder/__main__.py
terminator_layout_builder-0.1.1.dist-info/LICENSE
terminator_layout_builder-0.1.1.dist-info/METADATA
terminator_layout_builder-0.1.1.dist-info/WHEEL
terminator_layout_builder-0.1.1.dist-info/entry_points.txt
terminator_layout_builder-0.1.1.dist-info/top_level.txt
terminator_layout_builder-0.1.1.dist-info/RECORD
