Metadata-Version: 2.1
Name: terminator-layout-builder
Version: 0.1.1
Summary: A Terminator Terminal Layout Builder
Home-page: https://github.com/faizshukri/terminator-layout-builder
Author: Faiz Shukri
Author-email: faizshukri90@gmail.com
License: MIT
Platform: UNKNOWN
Classifier: License :: OSI Approved :: MIT License
Classifier: Programming Language :: Python
Classifier: Programming Language :: Python :: 3
Classifier: Operating System :: OS Independent
Requires-Python: >=3.6
Requires-Dist: configobj
Requires-Dist: pydash
Requires-Dist: pyyaml
Requires-Dist: expandvars
